cape_encrypt/__init__.py
cape_encrypt/cape_encrypt.py
cape_encrypt/cape_encrypt_test.py
cape_encrypt-0.1.1.dist-info/LICENSE
cape_encrypt-0.1.1.dist-info/METADATA
cape_encrypt-0.1.1.dist-info/WHEEL
cape_encrypt-0.1.1.dist-info/top_level.txt
cape_encrypt-0.1.1.dist-info/RECORD
