Metadata-Version: 2.1
Name: cape-encrypt
Version: 0.1.1
Summary: Encryption aid for functions running in Cape Enclaves
Author-email: Cape Privacy <contact@capeprivacy.com>
License: Apache License
Project-URL: repository, https://github.com/capeprivacy/pycape
Classifier: Programming Language :: Python
Requires-Python: >=3.7
License-File: LICENSE
